pypci/__init__.py
pypci/pypci.py
pypci-0.1.4.dist-info/LICENSE
pypci-0.1.4.dist-info/METADATA
pypci-0.1.4.dist-info/WHEEL
pypci-0.1.4.dist-info/top_level.txt
pypci-0.1.4.dist-info/RECORD
