Metadata-Version: 2.1
Name: pypci
Version: 0.1.4
Summary: PCI driver for python
Home-page: https://github.com/ars096/pypci
Author: Atsushi Nishimura
Author-email: ars096@gmail.com
License: MIT
Classifier: Programming Language :: Python :: 3
Classifier: License :: OSI Approved :: MIT License
License-File: LICENSE
Requires-Dist: portio
